notebookparams/__init__.py
notebookparams/notebookparams.py
notebookparams-0.2.dist-info/LICENSE
notebookparams-0.2.dist-info/METADATA
notebookparams-0.2.dist-info/WHEEL
notebookparams-0.2.dist-info/top_level.txt
notebookparams-0.2.dist-info/RECORD
