Metadata-Version: 2.1
Name: notebookparams
Version: 0.2
Summary: Provide parameters to notebooks
Home-page: https://github.com/mccoy04041991/CampaignContributionDemoCode
Author: Sachin Sharma
Author-email: sasharma@aimconsulting.com
License: MIT
Platform: UNKNOWN
